.DS_Store
public_data_food_analysis_3/.DS_Store
public_data_food_analysis_3/__init__.py
public_data_food_analysis_3/_nbdev.py
public_data_food_analysis_3/app_data.py
public_data_food_analysis_3/columbia.py
public_data_food_analysis_3/core.py
public_data_food_analysis_3/food_parser.py
public_data_food_analysis_3/data/correction_dic.pickle
public_data_food_analysis_3/data/parser_keys.csv
public_data_food_analysis_3-0.2.7.dist-info/LICENSE
public_data_food_analysis_3-0.2.7.dist-info/METADATA
public_data_food_analysis_3-0.2.7.dist-info/WHEEL
public_data_food_analysis_3-0.2.7.dist-info/entry_points.txt
public_data_food_analysis_3-0.2.7.dist-info/top_level.txt
public_data_food_analysis_3-0.2.7.dist-info/RECORD
