Metadata-Version: 2.1
Name: public-data-food-analysis-3
Version: 0.2.7
Summary: This project analyzes data from a few input sources.
Home-page: https://github.com/QiwenZz/public_data_food_analysis_3/tree/master/
Author: Qiwen Zhang, Jason Fleischer
Author-email: owenzhang1999@gmail.com
License: Apache Software License 2.0
Keywords: circadian ryhthm
Platform: UNKNOWN
Classifier: Development Status :: 3 - Alpha
Classifier: Intended Audience :: Developers
Classifier: Natural Language :: English
Classifier: Programming Language :: Python :: 3.6
Classifier: Programming Language :: Python :: 3.7
Classifier: Programming Language :: Python :: 3.8
Classifier: License :: OSI Approved :: Apache Software License
Requires-Python: >=3.6
Requires-Dist: pip
Requires-Dist: packaging
Requires-Dist: pandas
Requires-Dist: numpy
Requires-Dist: scipy
Requires-Dist: seaborn
Requires-Dist: matplotlib
Requires-Dist: datetime
Requires-Dist: nltk
Provides-Extra: dev
